{
  "project_info": {
    "project_number": "204647889968",
    "firebase_url": "https://basic-firebase-29c26-default-rtdb.asia-southeast1.firebasedatabase.app",
    "project_id": "basic-firebase-29c26",
    "storage_bucket": "basic-firebase-29c26.appspot.com"
  },
  "client": [
    {
      "client_info": {
        "mobilesdk_app_id": "1:204647889968:android:7a70cf3705835a66f341f5",
        "android_client_info": {
          "package_name": "com.example.firebaseapp"
        }
      },
      "oauth_client": [
        {
          "client_id": "204647889968-lcm7sokek5720u095s6s1bocnevsgrk7.apps.googleusercontent.com",
          "client_type": 3
        }
      ],
      "api_key": [
        {
          "current_key": "AIzaSyCOf0pHUiOOZ73oksJ9fpQnu3idyId6uUU"
        }
      ],
      "services": {
        "appinvite_service": {
          "other_platform_oauth_client": [
            {
              "client_id": "204647889968-lcm7sokek5720u095s6s1bocnevsgrk7.apps.googleusercontent.com",
              "client_type": 3
            }
          ]
        }
      }
    },
    {
      "client_info": {
        "mobilesdk_app_id": "1:204647889968:android:c4446ded3f752de3f341f5",
        "android_client_info": {
          "package_name": "com.example.qrcodescanner"
        }
      },
      "oauth_client": [
        {
          "client_id": "204647889968-lcm7sokek5720u095s6s1bocnevsgrk7.apps.googleusercontent.com",
          "client_type": 3
        }
      ],
      "api_key": [
        {
          "current_key": "AIzaSyCOf0pHUiOOZ73oksJ9fpQnu3idyId6uUU"
        }
      ],
      "services": {
        "appinvite_service": {
          "other_platform_oauth_client": [
            {
              "client_id": "204647889968-lcm7sokek5720u095s6s1bocnevsgrk7.apps.googleusercontent.com",
              "client_type": 3
            }
          ]
        }
      }
    }
  ],
  "configuration_version": "1"
}